optht/__init__.py
optht/optht.py
optht-0.2.0.dist-info/LICENSE
optht-0.2.0.dist-info/METADATA
optht-0.2.0.dist-info/WHEEL
optht-0.2.0.dist-info/top_level.txt
optht-0.2.0.dist-info/RECORD
