Metadata-Version: 2.1
Name: optht
Version: 0.2.0
Summary: Optimal hard threshold for matrix denoising
Home-page: https://github.com/erichson/optht
Author: N. Benjamin Erichson, Steven Dahdah
Author-email: erichson@berkeley.edu, Steven.Dahdah@mail.mcgill.ca
License: UNKNOWN
Project-URL: Bug Tracker, https://github.com/erichson/optht/issues
Platform: UNKNOWN
Classifier: Programming Language :: Python :: 3
Classifier: License :: OSI Approved :: GNU General Public License v3 (GPLv3)
Classifier: Operating System :: OS Independent
Requires-Python: >=3.6
Requires-Dist: numpy
Requires-Dist: scipy
